netmiko_bridge_vendor/__init__.py
netmiko_bridge_vendor/bdcom/__init__.py
netmiko_bridge_vendor/bdcom/bdcom.py
netmiko_bridge_vendor-0.1.0.dist-info/LICENSE
netmiko_bridge_vendor-0.1.0.dist-info/METADATA
netmiko_bridge_vendor-0.1.0.dist-info/WHEEL
netmiko_bridge_vendor-0.1.0.dist-info/top_level.txt
netmiko_bridge_vendor-0.1.0.dist-info/RECORD
