Metadata-Version: 2.1
Name: netmiko-bridge-vendor
Version: 0.1.0
Summary: Netmiko vendor driver extension with netmiko bridge support.
Author-email: "shuai w." <x@ousui.org>
License: MIT License
Project-URL: Homepage, https://github.com/ousui/netmiko_bridge_vendor
Project-URL: Bug Tracker, https://github.com/ousui/netmiko_bridge_vendor/issues
Keywords: netmiko
Classifier: Programming Language :: Python :: 3
Classifier: License :: OSI Approved :: MIT License
Classifier: Operating System :: OS Independent
Requires-Python: >=3.6
License-File: LICENSE
Requires-Dist: netmiko
Requires-Dist: netmiko-bridge
